asciii.py
asciii-1.0.13.dist-info/WHEEL
asciii-1.0.13.dist-info/METADATA
asciii-1.0.13.dist-info/RECORD
