Metadata-Version: 2.1
Name: asciii
Version: 1.0.13
Summary: A library that converts images to ascii
Author: acup1
Author-email: georgiyegoriy@gmail.com
Requires-Python: >=3.7,<4.0
Classifier: Programming Language :: Python :: 3
Classifier: Programming Language :: Python :: 3.10
Classifier: Programming Language :: Python :: 3.7
Classifier: Programming Language :: Python :: 3.8
Classifier: Programming Language :: Python :: 3.9
Requires-Dist: Pillow (>=9.0.1,<10.0.0)
